{
	"action" : "display",
	"index" : 76,
	"imagelist" : [
		{
			"imagelist" : "7600.jpg",
			"X" : "836",
			"Y" : "116",
			"rectX" : "48",
			"rectY" : "26"
		},
		{
			"imagelist" : "7601.jpg",
			"X" : "900",
			"Y" : "142",
			"rectX" : "48",
			"rectY" : "16"
		},
		{
			"imagelist" : "7602.jpg",
			"X" : "868",
			"Y" : "158",
			"rectX" : "16",
			"rectY" : "16"
		},
		{
			"imagelist" : "7603.jpg",
			"X" : "804",
			"Y" : "174",
			"rectX" : "16",
			"rectY" : "16"
		},
		{
			"imagelist" : "7604.jpg",
			"X" : "804",
			"Y" : "204",
			"rectX" : "432",
			"rectY" : "16"
		},
		{
			"imagelist" : "7605.jpg",
			"X" : "884",
			"Y" : "220",
			"rectX" : "64",
			"rectY" : "16"
		},
		{
			"imagelist" : "7606.jpg",
			"X" : "836",
			"Y" : "236",
			"rectX" : "48",
			"rectY" : "16"
		},
		{
			"imagelist" : "7607.jpg",
			"X" : "900",
			"Y" : "252",
			"rectX" : "48",
			"rectY" : "16"
		},
		{
			"imagelist" : "7608.jpg",
			"X" : "868",
			"Y" : "268",
			"rectX" : "16",
			"rectY" : "16"
		},
		{
			"imagelist" : "7609.jpg",
			"X" : "100",
			"Y" : "284",
			"rectX" : "160",
			"rectY" : "16"
		},
		{
			"imagelist" : "7610.jpg",
			"X" : "804",
			"Y" : "284",
			"rectX" : "16",
			"rectY" : "16"
		},
		{
			"imagelist" : "7611.jpg",
			"X" : "100",
			"Y" : "300",
			"rectX" : "160",
			"rectY" : "16"
		},
		{
			"imagelist" : "7612.jpg",
			"X" : "100",
			"Y" : "316",
			"rectX" : "160",
			"rectY" : "16"
		},
		{
			"imagelist" : "7613.jpg",
			"X" : "804",
			"Y" : "316",
			"rectX" : "432",
			"rectY" : "16"
		},
		{
			"imagelist" : "7614.jpg",
			"X" : "884",
			"Y" : "332",
			"rectX" : "64",
			"rectY" : "16"
		},
		{
			"imagelist" : "7615.jpg",
			"X" : "836",
			"Y" : "348",
			"rectX" : "48",
			"rectY" : "16"
		},
		{
			"imagelist" : "7616.jpg",
			"X" : "900",
			"Y" : "364",
			"rectX" : "48",
			"rectY" : "16"
		},
		{
			"imagelist" : "7617.jpg",
			"X" : "868",
			"Y" : "380",
			"rectX" : "16",
			"rectY" : "16"
		},
		{
			"imagelist" : "7618.jpg",
			"X" : "804",
			"Y" : "396",
			"rectX" : "16",
			"rectY" : "16"
		},
		{
			"imagelist" : "7619.jpg",
			"X" : "804",
			"Y" : "428",
			"rectX" : "48",
			"rectY" : "16"
		},
		{
			"imagelist" : "7620.jpg",
			"X" : "1060",
			"Y" : "428",
			"rectX" : "32",
			"rectY" : "16"
		},
		{
			"imagelist" : "7621.jpg",
			"X" : "1188",
			"Y" : "428",
			"rectX" : "32",
			"rectY" : "16"
		},
		{
			"imagelist" : "7622.jpg",
			"X" : "884",
			"Y" : "444",
			"rectX" : "48",
			"rectY" : "16"
		},
		{
			"imagelist" : "7623.jpg",
			"X" : "836",
			"Y" : "460",
			"rectX" : "48",
			"rectY" : "16"
		}
	]
}